<Waves>
	<Wave BeforeWaveDelay="3">
		<Enemy Type="Popcorn" Spawn="0" Y="6" />
		<Enemy Type="Popcorn" Spawn="0" Y="2" />
		<Enemy Type="Popcorn" Spawn="2" Y="6" />
		<Enemy Type="Popcorn" Spawn="2" Y="2" />
		<Enemy Type="Popcorn" Spawn="4" Y="6" />
		<Enemy Type="Popcorn" Spawn="4" Y="2" />
		<Enemy Type="Popcorn" Spawn="6" Y="6" />
		<Enemy Type="Popcorn" Spawn="6" Y="2" />
		
		<Enemy Type="Popcorn" Spawn="8" Y="5" />
		<Enemy Type="Popcorn" Spawn="9" Y="3" />
		<Enemy Type="Popcorn" Spawn="10" Y="5" />
		<Enemy Type="Popcorn" Spawn="11" Y="3" />
		<Enemy Type="Popcorn" Spawn="12" Y="5" />
		<Enemy Type="Popcorn" Spawn="13" Y="3" />
		<Enemy Type="Popcorn" Spawn="14" Y="5" />
		<Enemy Type="Popcorn" Spawn="15" Y="3" />
		
		<Enemy Type="Popcorn" Spawn="16" Y="4" />
		<Enemy Type="Popcorn" Spawn="16.25" Y="2" />
		<Enemy Type="Popcorn" Spawn="16.5" Y="5" />
		<Enemy Type="Popcorn" Spawn="16.75" Y="6" />
		<Enemy Type="Popcorn" Spawn="17" Y="4" />
		<Enemy Type="Popcorn" Spawn="17.25" Y="2" />
		<Enemy Type="Popcorn" Spawn="17.5" Y="5" />
		<Enemy Type="Popcorn" Spawn="17.75" Y="6" />
	</Wave>
</Waves>